{
  "id": "",
  "name": "",
  "font_family": "iconfont",
  "css_prefix_text": "icon-",
  "description": "",
  "glyphs": [
    {
      "icon_id": "577313",
      "name": "加号1",
      "font_class": "jiahao1",
      "unicode": "e727",
      "unicode_decimal": 59175
    },
    {
      "icon_id": "789130",
      "name": "客户服务  客服",
      "font_class": "kehufuwukefu",
      "unicode": "e698",
      "unicode_decimal": 59032
    },
    {
      "icon_id": "6775644",
      "name": "爱心",
      "font_class": "aixin",
      "unicode": "eca1",
      "unicode_decimal": 60577
    }
  ]
}
